FITSImageQA/__init__.py
FITSImageQA/imageqa.py
FITSImageQA/detection/__init__.py
FITSImageQA/detection/detection.py
FITSImageQA/detection/detection_mrf.py
FITSImageQA-0.0.3.dist-info/LICENSE.md
FITSImageQA-0.0.3.dist-info/METADATA
FITSImageQA-0.0.3.dist-info/WHEEL
FITSImageQA-0.0.3.dist-info/top_level.txt
FITSImageQA-0.0.3.dist-info/RECORD
