Metadata-Version: 2.1
Name: FITSImageQA
Version: 0.0.3
Summary: Perform quality checks on FITS images
Home-page: https://github.com/wpb-astro/FITSImageQA
License: MIT
Classifier: Programming Language :: Python :: 3
Classifier: License :: OSI Approved :: MIT License
Classifier: Intended Audience :: Developers
Classifier: Intended Audience :: Science/Research
Classifier: Operating System :: OS Independent
Classifier: Topic :: Scientific/Engineering :: Astronomy
Requires-Python: >=3.7
License-File: LICENSE.md
